magic_config/__init__.py
magic_config/lib.py
magic_config-0.1.13.dist-info/LICENSE
magic_config-0.1.13.dist-info/METADATA
magic_config-0.1.13.dist-info/WHEEL
magic_config-0.1.13.dist-info/top_level.txt
magic_config-0.1.13.dist-info/RECORD
